__init__.py
_voxelpic.cpython-310-x86_64-linux-gnu.so
voxelpic.py
voxelpic-0.1.0.dist-info/METADATA
voxelpic-0.1.0.dist-info/WHEEL
voxelpic-0.1.0.dist-info/top_level.txt
voxelpic-0.1.0.dist-info/RECORD
voxelpic-0.1.0.dist-info/licenses/LICENSE.md
