Metadata-Version: 2.4
Name: voxelpic
Version: 0.1.0
Summary: voxelpic is a Python module which transcodes point clouds to and from images.
Author-email: Matthew Johnson <matjoh@microsoft.com>
License-Expression: MIT
Keywords: voxel,3D
Classifier: Programming Language :: Python :: 3
Requires-Python: >=3.8
License-File: LICENSE.md
Requires-Dist: numpy
Provides-Extra: test
Requires-Dist: pytest-md; extra == "test"
Requires-Dist: pytest-emoji; extra == "test"
Requires-Dist: pytest-cov; extra == "test"
Requires-Dist: pytest; extra == "test"
Dynamic: license-file
